camera_calib/__init__.py
camera_calib/_nbdev.py
camera_calib/api.py
camera_calib/calib.py
camera_calib/cb_geom.py
camera_calib/control_refine.py
camera_calib/fiducial_detect.py
camera_calib/image.py
camera_calib/modules.py
camera_calib/plot.py
camera_calib/utils.py
nbdev_template/__init__.py
nbdev_template/_nbdev.py
nbdev_template/modules.py
camera_calib-0.0.4.dist-info/LICENSE
camera_calib-0.0.4.dist-info/METADATA
camera_calib-0.0.4.dist-info/WHEEL
camera_calib-0.0.4.dist-info/entry_points.txt
camera_calib-0.0.4.dist-info/top_level.txt
camera_calib-0.0.4.dist-info/RECORD
